docs/__init__.py
hamhelper/__init__.py
hamhelper/colours.py
hamhelper/errors.py
hamhelper/plotting.py
hamhelper-1.13.dist-info/LICENSE
hamhelper-1.13.dist-info/METADATA
hamhelper-1.13.dist-info/WHEEL
hamhelper-1.13.dist-info/top_level.txt
hamhelper-1.13.dist-info/RECORD
